eva/__init__.py
eva/eva.py
everythingisevangelion-0.1.0.dist-info/LICENSE.txt
everythingisevangelion-0.1.0.dist-info/METADATA
everythingisevangelion-0.1.0.dist-info/WHEEL
everythingisevangelion-0.1.0.dist-info/top_level.txt
everythingisevangelion-0.1.0.dist-info/RECORD
