Metadata-Version: 2.1
Name: everythingisevangelion
Version: 0.1.0
Summary: Pathfinder from any Wikipedia article to Neon Genesis Evangelion
Home-page: https://github.com/mwlk1/everythingisevangelion
Author: mwlk1
Classifier: Programming Language :: Python :: 3
Classifier: License :: OSI Approved :: MIT License
Classifier: Operating System :: OS Independent
Requires-Python: >=3.6
License-File: LICENSE.txt
Requires-Dist: requests
Requires-Dist: beautifulsoup4
